BellaCiao/BellaCiao.py
BellaCiao/__init__.py
BellaCiao/bellaml.py
Bella_Ciao-0.0.1.dist-info/License
Bella_Ciao-0.0.1.dist-info/METADATA
Bella_Ciao-0.0.1.dist-info/WHEEL
Bella_Ciao-0.0.1.dist-info/top_level.txt
Bella_Ciao-0.0.1.dist-info/RECORD
