Metadata-Version: 2.1
Name: Bella-Ciao
Version: 0.0.1
Summary: Bella Ciao Package
Home-page: https://github.com/BellaCiao2020/BellaCiao
Author: Samācāraṁ Śāstravētta
Author-email: bella.ciao.062020@gmail.com
License: UNKNOWN
Platform: UNKNOWN
Classifier: Programming Language :: Python :: 3
Classifier: License :: OSI Approved :: MIT License
Classifier: Operating System :: OS Independent
Requires-Python: >=3.6
